sphinxcontrib/yowasp_wavedrom.py
sphinxcontrib_yowasp_wavedrom-1.8.dist-info/METADATA
sphinxcontrib_yowasp_wavedrom-1.8.dist-info/WHEEL
sphinxcontrib_yowasp_wavedrom-1.8.dist-info/licenses/LICENSE.txt
sphinxcontrib_yowasp_wavedrom-1.8.dist-info/RECORD
