Metadata-Version: 2.1
Name: sphinxcontrib-yowasp-wavedrom
Version: 1.8
Summary: A Sphinx extension for embedding WaveDrom diagrams
Author-Email: Catherine <whitequark@whitequark.org>
License: MIT
Classifier: License :: OSI Approved :: MIT License
Requires-Python: ~=3.8
Requires-Dist: importlib_resources; python_version < "3.9"
Requires-Dist: Sphinx~=7.1
Requires-Dist: yowasp-wavedrom>=3.5.0.8
Requires-Dist: json5~=0.9
